main.py
simpledevsecops-0.1.1.dist-info/METADATA
simpledevsecops-0.1.1.dist-info/WHEEL
simpledevsecops-0.1.1.dist-info/entry_points.txt
simpledevsecops-0.1.1.dist-info/top_level.txt
simpledevsecops-0.1.1.dist-info/RECORD
