Metadata-Version: 2.4
Name: simpledevsecops
Version: 0.1.1
Summary: Interactive DevSecOps Pipeline Generator
Author-email: Sourav Kumar Singh <1109souravkumar@gmail.com>
Requires-Python: >=3.8
Requires-Dist: PyYAML
